sqlalchemy_signing/__init__.py
sqlalchemy_signing/__metadata__.py
sqlalchemy_signing-1.0.8.dist-info/licenses/LICENSE
tests/__init__.py
sqlalchemy_signing-1.0.8.dist-info/METADATA
sqlalchemy_signing-1.0.8.dist-info/WHEEL
sqlalchemy_signing-1.0.8.dist-info/top_level.txt
sqlalchemy_signing-1.0.8.dist-info/RECORD
